normtest/__init__.py
normtest/bibmaker.py
normtest/filliben.py
normtest/looney_gulledge.py
normtest/ryan_joiner.py
normtest/version.py
normtest/utils/__init__py
normtest/utils/constants.py
normtest/utils/critical_values.py
normtest/utils/documentation.py
normtest/utils/helpers.py
normtest-0.0.3.dist-info/LICENSE
normtest-0.0.3.dist-info/METADATA
normtest-0.0.3.dist-info/WHEEL
normtest-0.0.3.dist-info/top_level.txt
normtest-0.0.3.dist-info/RECORD
