Metadata-Version: 2.1
Name: normtest
Version: 0.0.3
Summary: Check that your data follows, at least approximately, the Normal distribution.
Author-email: Anderson Marcos Dias Canteli <andersonmdcanteli@gmail.com>
License: BSD 3-Clause License
Project-URL: Source, https://github.com/puzzle-in-a-mug/normtest
Project-URL: Docs, https://normtest.readthedocs.io/en/latest/index.html
Keywords: normality,sample,test
Classifier: Development Status :: 3 - Alpha
Classifier: Intended Audience :: Science/Research
Classifier: License :: OSI Approved :: BSD License
Classifier: Operating System :: OS Independent
Classifier: Programming Language :: Python :: 3 :: Only
Classifier: Programming Language :: Python :: 3.10
Classifier: Programming Language :: Python :: 3.11
Classifier: Programming Language :: Python :: 3.12
Requires-Python: >=3.10
License-File: LICENSE
Requires-Dist: numpy >=1.23.5
Requires-Dist: pandas >=1.5.3
Requires-Dist: matplotlib >=3.7.1
Requires-Dist: scipy >=1.11.3
Requires-Dist: paramcheckup >=1.0.1
